{
  "id": "developer-sandbox",
  "label": "Fejlesztő (elszigetelt)",
  "description": "Kód-fejlesztés a saját, elszigetelt munkamappában. A main/master-re tiltott a push, sudo tiltva, SSH/AWS/GnuPG kulcsok elrejtve. Csak a saját mappájába ír. A TSD (fejlesztő) és a SAE (automatizáló) osztja ezt a profilt; az éles kifelé-hatás (telepítés/indítás) kapuzott, nem az ügynök végzi élőben.",
  "permissionMode": "strict",
  "filesystem": {
    "allow": [
      "Read(${AGENT_DIR}/**)",
      "Write(${AGENT_DIR}/**)",
      "Edit(${AGENT_DIR}/**)",
      "Read(/tmp/**)",
      "Write(/tmp/**)",
      "Bash(git:*)",
      "Bash(npm:*)",
      "Bash(node:*)",
      "Bash(python3:*)",
      "Bash(ls:*)",
      "Bash(cat:*)",
      "Bash(pwd:*)",
      "Bash(curl:*)",
      "WebFetch(*)",
      "WebSearch(*)"
    ],
    "deny": [
      "Read(${HOME}/.ssh/**)",
      "Read(${HOME}/.aws/**)",
      "Read(${HOME}/.gnupg/**)",
      "Bash(sudo:*)",
      "Bash(rm -rf ${HOME}:*)",
      "Bash(git push --force:*)",
      "Bash(git push -f:*)",
      "Bash(git push origin main:*)",
      "Bash(git push origin master:*)"
    ]
  }
}
